README.md
setup.py
mara_markdown_docs/__init__.py
mara_markdown_docs/config.py
mara_markdown_docs/docs.py
mara_markdown_docs.egg-info/PKG-INFO
mara_markdown_docs.egg-info/SOURCES.txt
mara_markdown_docs.egg-info/dependency_links.txt
mara_markdown_docs.egg-info/requires.txt
mara_markdown_docs.egg-info/top_level.txt
tests/__init__.py
tests/test_mara_markdown_docs.py