Metadata-Version: 2.1
Name: mara-markdown-docs
Version: 0.9.0
Summary: Display markdown documentation in mara UI
Home-page: https://github.com/jankatins/mara-markdown-docs
Author: Mara contributors
License: MIT
Platform: UNKNOWN
Requires-Python: >=3.7
